src/flashvideo/distill.py
src/flashvideo/distill_adv.py
src/flashvideo/train.py
src/flashvideo/data_preprocess/preprocess_text_embeddings.py
src/flashvideo/data_preprocess/preprocess_vae_latents.py
src/flashvideo/data_preprocess/preprocess_validation_text_embeddings.py
src/flashvideo/dataset/__init__.py
src/flashvideo/dataset/latent_datasets.py
src/flashvideo/dataset/t2v_datasets.py
src/flashvideo/dataset/transform.py
src/flashvideo/distill/__init__.py
src/flashvideo/distill/discriminator.py
src/flashvideo/distill/solver.py
src/flashvideo/models/flash_attn_no_pad.py
src/flashvideo/models/hunyuan/__init__.py
src/flashvideo/models/hunyuan/constants.py
src/flashvideo/models/hunyuan/idle_config.py
src/flashvideo/models/hunyuan/inference.py
src/flashvideo/models/hunyuan/prompt_rewrite.py
src/flashvideo/models/hunyuan/diffusion/__init__.py
src/flashvideo/models/hunyuan/diffusion/pipelines/__init__.py
src/flashvideo/models/hunyuan/diffusion/pipelines/pipeline_hunyuan_video.py
src/flashvideo/models/hunyuan/diffusion/schedulers/__init__.py
src/flashvideo/models/hunyuan/diffusion/schedulers/scheduling_flow_match_discrete.py
src/flashvideo/models/hunyuan/modules/__init__.py
src/flashvideo/models/hunyuan/modules/activation_layers.py
src/flashvideo/models/hunyuan/modules/attenion.py
src/flashvideo/models/hunyuan/modules/embed_layers.py
src/flashvideo/models/hunyuan/modules/mlp_layers.py
src/flashvideo/models/hunyuan/modules/models.py
src/flashvideo/models/hunyuan/modules/modulate_layers.py
src/flashvideo/models/hunyuan/modules/norm_layers.py
src/flashvideo/models/hunyuan/modules/posemb_layers.py
src/flashvideo/models/hunyuan/modules/token_refiner.py
src/flashvideo/models/hunyuan/text_encoder/__init__.py
src/flashvideo/models/hunyuan/utils/__init__.py
src/flashvideo/models/hunyuan/utils/data_utils.py
src/flashvideo/models/hunyuan/utils/file_utils.py
src/flashvideo/models/hunyuan/utils/helpers.py
src/flashvideo/models/hunyuan/utils/preprocess_text_encoder_tokenizer_utils.py
flashvideo-0.1.0.dist-info/LICENSE
flashvideo-0.1.0.dist-info/METADATA
flashvideo-0.1.0.dist-info/WHEEL
flashvideo-0.1.0.dist-info/top_level.txt
flashvideo-0.1.0.dist-info/RECORD
